byerecaptcha/__init__.py
byerecaptcha/byerecaptcha.py
byerecaptcha-1.2.4.dist-info/LICENSE
byerecaptcha-1.2.4.dist-info/METADATA
byerecaptcha-1.2.4.dist-info/WHEEL
byerecaptcha-1.2.4.dist-info/top_level.txt
byerecaptcha-1.2.4.dist-info/RECORD
