Metadata-Version: 2.1
Name: byerecaptcha
Version: 1.2.4
Summary: Google Recaptcha solver with selenium.
Home-page: https://github.com/DedInc/byerecaptcha
Author: Maehdakvan
Author-email: visitanimation@google.com
Project-URL: Bug Tracker, https://github.com/DedInc/byerecaptcha/issues
Classifier: Programming Language :: Python :: 3
Classifier: License :: OSI Approved :: MIT License
Classifier: Operating System :: OS Independent
Requires-Python: >=3.6
License-File: LICENSE
Requires-Dist: opencv-python (==4.6.0.66)
Requires-Dist: Pillow
Requires-Dist: numpy
Requires-Dist: requests
Requires-Dist: selenium (>=4.7.0)
